pyclibrary/__init__.py
pyclibrary/c_library.py
pyclibrary/c_parser.py
pyclibrary/errors.py
pyclibrary/init.py
pyclibrary/utils.py
pyclibrary/version.py
pyclibrary/backends/__init__.py
pyclibrary/backends/ctypes.py
pyclibrary/headers/README
pyclibrary/headers/WinDefs.cache
pyclibrary/headers/update_WinDefs.py
pyclibrary/thirdparty/__init__.py
pyclibrary/thirdparty/find_library.py
pyclibrary/thirdparty/pyparsing.py
pyclibrary_aagallag-0.1.4.dist-info/DESCRIPTION.rst
pyclibrary_aagallag-0.1.4.dist-info/METADATA
pyclibrary_aagallag-0.1.4.dist-info/RECORD
pyclibrary_aagallag-0.1.4.dist-info/WHEEL
pyclibrary_aagallag-0.1.4.dist-info/metadata.json
pyclibrary_aagallag-0.1.4.dist-info/top_level.txt
