Metadata-Version: 2.0
Name: pyclibrary-aagallag
Version: 0.1.4
Summary: C binding automation
Home-page: http://github.com/aagallag/pyclibrary
Author: Aaron Gallagher
Author-email: aaron.b.gallagher@gmail.com
License: MIT
Download-URL: http://github.com/aagallag/pyclibrary/tarball/master
Keywords: C binding automation
Platform: UNKNOWN
Classifier: Development Status :: 3 - Alpha
Classifier: Environment :: Console
Classifier: License :: OSI Approved :: MIT License
Classifier: Natural Language :: English
Classifier: Operating System :: OS Independent
Classifier: Topic :: Software Development :: Libraries :: Python Modules
Classifier: Programming Language :: Python :: 2
Classifier: Programming Language :: Python :: 3
Requires: future
Requires-Dist: future
